kneefinder/__init__.py
kneefinder/kneefinder.py
kneefinder-0.0.2.dist-info/LICENSE
kneefinder-0.0.2.dist-info/METADATA
kneefinder-0.0.2.dist-info/WHEEL
kneefinder-0.0.2.dist-info/top_level.txt
kneefinder-0.0.2.dist-info/RECORD
