Metadata-Version: 2.1
Name: kneefinder
Version: 0.0.2
Summary: A simple tool to find the `knee` point of a 2-d curve.
Home-page: https://github.com/vlavorini/kneefinder
Author: Vincenzo Lavorini
Author-email: vincenzo.lavorini@protonmail.ch
License: BSD 2-clause
Classifier: Development Status :: 3 - Alpha
Classifier: Intended Audience :: Science/Research
Classifier: License :: OSI Approved :: BSD License
Classifier: Operating System :: POSIX :: Linux
Classifier: Programming Language :: Python :: 3
Classifier: Programming Language :: Python :: 3.9
Classifier: Programming Language :: Python :: 3.10
License-File: LICENSE
Requires-Dist: numpy
Requires-Dist: matplotlib
